sqlalchemy_zen/__init__.py
sqlalchemy_zen/base.py
sqlalchemy_zen/ddl_elements.py
sqlalchemy_zen/ddl_generator.py
sqlalchemy_zen/ddl_utils.py
sqlalchemy_zen/dialect.py
sqlalchemy_zen/provision.py
sqlalchemy_zen/pytest_plugin.py
sqlalchemy_zen/requirements.py
sqlalchemy_zen/types.py
sqlalchemy_zen-16.10.0.dist-info/METADATA
sqlalchemy_zen-16.10.0.dist-info/WHEEL
sqlalchemy_zen-16.10.0.dist-info/entry_points.txt
sqlalchemy_zen-16.10.0.dist-info/licenses/LICENSE.txt
sqlalchemy_zen-16.10.0.dist-info/RECORD
