Metadata-Version: 2.4
Name: sqlalchemy-zen
Version: 16.10.0
Summary: SQLAlchemy Dialect for Actian Zen (ODBC only)
Author: Actian Corporation
License: Copyright (c) 2025 Actian Corporation. All rights reserved.
License-File: LICENSE.txt
Classifier: Development Status :: 3 - Alpha
Classifier: Intended Audience :: Developers
Classifier: License :: Other/Proprietary License
Classifier: Operating System :: OS Independent
Classifier: Programming Language :: Python
Classifier: Programming Language :: Python :: 3
Classifier: Programming Language :: SQL
Classifier: Topic :: Database
Requires-Dist: pyodbc
Requires-Dist: sqlalchemy>=2.0.1
Provides-Extra: dev
Requires-Dist: black>=22.0.0; extra == 'dev'
Requires-Dist: flake8>=5.0.0; extra == 'dev'
Requires-Dist: mypy>=1.0.0; extra == 'dev'
Provides-Extra: test
Requires-Dist: mock>=4.0.0; extra == 'test'
Requires-Dist: pytest-cov>=4.0.0; extra == 'test'
Requires-Dist: pytest>=7.0.0; extra == 'test'
Requires-Dist: tox>=4.0.0; extra == 'test'
